code_agent/.gitignore
code_agent/__init__.py
code_agent/agents/__init__.py
code_agent/agents/code_audit.py
code_agent/agents/code_refactorer.py
code_agent/agents/commit_maker.py
code_agent/cli.py
code_agent/config.py
code_agent/definitions.py
code_agent/output_schemas/AuditReport.py
code_agent/output_schemas/CodeSuggestions.py
code_agent/output_schemas/CommitMessage.py
code_agent/output_schemas/__init__.py
code_agent/settings/code_audit_config.toml
code_agent/settings/code_refactorer_config.toml
code_agent/settings/commit_maker_config.toml
code_agent/utils/__init__.py
code_agent/utils/git/__init__.py
code_agent/utils/git/git_local.py
code_agent/utils/read_text.py
code_agent-0.3.0.1.dist-info/METADATA
code_agent-0.3.0.1.dist-info/WHEEL
code_agent-0.3.0.1.dist-info/entry_points.txt
code_agent-0.3.0.1.dist-info/RECORD
