Metadata-Version: 2.1
Name: code-agent
Version: 0.3.0.1
Summary: 🦾 🤖 ChatGPT-based Agent tool for support your software development.
Home-page: https://github.com/Gonsix/Code-Agent
License: MIT
Keywords: ChatGPT,LangChain,LLM,AI-Tool,Git
Author: Shingo Morimoto
Author-email: gonsix3@gmail.com
Maintainer: Shingo Morimoto
Maintainer-email: gonsix3@gmail.com
Requires-Python: >=3.9,<4.0
Classifier: License :: OSI Approved :: MIT License
Classifier: Programming Language :: Python :: 3
Classifier: Programming Language :: Python :: 3.9
Classifier: Programming Language :: Python :: 3.10
Classifier: Programming Language :: Python :: 3.11
Classifier: Programming Language :: Python :: 3.12
Requires-Dist: dynaconf (>=3.2.4,<4.0.0)
Requires-Dist: gitpython (>=3.1.42,<4.0.0)
Requires-Dist: langchain (>=0.1.10,<0.2.0)
Requires-Dist: langchain-community (>=0.0.25,<0.0.26)
Requires-Dist: langchain-openai (>=0.0.8,<0.0.9)
Requires-Dist: openai (>=1.13.3,<2.0.0)
Requires-Dist: python-dotenv (>=1.0.1,<2.0.0)
Requires-Dist: rich (>=13.7.1,<14.0.0)
Requires-Dist: typer[all] (>=0.9.0,<0.10.0)
Project-URL: Repository, https://github.com/Gonsix/Code-Agent
